task1/counter.sv
module counter #(
  parameter WIDTH = 8
)(
  input logic clk,
  input logic rst,
  input logic en,
  output logic [WIDTH-1:0] count
);

always_ff @ (posedge clk)
  if (rst) count <= {WIDTH{1'b0}};
  else count <= count + {{WIDTH-1{1'b0}}, en};

endmodule

task1/counter.vcd
$version Generated by VerilatedVcd $end
$timescale 1ps $end
 $scope module TOP $end
  $var wire 1 # clk $end
  $var wire 1 $ rst $end
  $var wire 1 % en $end
  $var wire 8 & count [7:0] $end
  $scope module counter $end
   $var wire 32 ' WIDTH [31:0] $end
   $var wire 1 # clk $end
   $var wire 1 $ rst $end
   $var wire 1 % en $end
   $var wire 8 & count [7:0] $end
  $upscope $end
 $upscope $end
$enddefinitions $end


#0
1#
1$
0%
b00000000 &
b00000000000000000000000000001000 '
#1
0#
#2
1#
1%
#3
0#
#4
1#
#5
0#
#6
1#
0$
#7
0#
#8
1#
b00000001 &
#9
0#
#10
1#
b00000010 &
#11
0#
#12
1#
b00000011 &
#13
0#
#14
1#
b00000100 &
#15
0#
#16
1#
b00000101 &
#17
0#
#18
1#
b00000110 &
#19
0#
#20
1#
b00000111 &
#21
0#
#22
1#
b00001000 &
#23
0#
#24
1#
b00001001 &
#25
0#
#26
1#
b00001010 &
#27
0#
#28
1#
b00001011 &
#29
0#
#30
1#
b00001100 &
#31
0#
#32
1#
1$
b00001101 &
#33
0#
#34
1#
0$
b00000000 &
#35
0#
#36
1#
b00000001 &
#37
0#
#38
1#
b00000010 &
#39
0#
#40
1#
b00000011 &
#41
0#
#42
1#
b00000100 &
#43
0#
#44
1#
b00000101 &
#45
0#
#46
1#
b00000110 &
#47
0#
#48
1#
b00000111 &
#49
0#
#50
1#
b00001000 &
#51
0#
#52
1#
b00001001 &
#53
0#
#54
1#
b00001010 &
#55
0#
#56
1#
b00001011 &
#57
0#
#58
1#
b00001100 &
#59
0#
#60
1#
b00001101 &
#61
0#
#62
1#
b00001110 &
#63
0#
#64
1#
b00001111 &
#65
0#
#66
1#
b00010000 &
#67
0#
#68
1#
b00010001 &
#69
0#
#70
1#
b00010010 &
#71
0#
#72
1#
b00010011 &
#73
0#
#74
1#
b00010100 &
#75
0#
#76
1#
b00010101 &
#77
0#
#78
1#
b00010110 &
#79
0#
#80
1#
b00010111 &
#81
0#
#82
1#
b00011000 &
#83
0#
#84
1#
b00011001 &
#85
0#
#86
1#
b00011010 &
#87
0#
#88
1#
b00011011 &
#89
0#
#90
1#
b00011100 &
#91
0#
#92
1#
b00011101 &
#93
0#
#94
1#
b00011110 &
#95
0#
#96
1#
b00011111 &
#97
0#
#98
1#
b00100000 &
#99
0#
#100
1#
b00100001 &
#101
0#
#102
1#
b00100010 &
#103
0#
#104
1#
b00100011 &
#105
0#
#106
1#
b00100100 &
#107
0#
#108
1#
b00100101 &
#109
0#
#110
1#
b00100110 &
#111
0#
#112
1#
b00100111 &
#113
0#
#114
1#
0%
b00101000 &
